conductorquantum/__init__.py
conductorquantum/base_client.py
conductorquantum/client.py
conductorquantum/core/__init__.py
conductorquantum/core/api_error.py
conductorquantum/core/client_wrapper.py
conductorquantum/core/datetime_utils.py
conductorquantum/core/file.py
conductorquantum/core/force_multipart.py
conductorquantum/core/http_client.py
conductorquantum/core/http_response.py
conductorquantum/core/jsonable_encoder.py
conductorquantum/core/pydantic_utilities.py
conductorquantum/core/query_encoder.py
conductorquantum/core/remove_none_from_dict.py
conductorquantum/core/request_options.py
conductorquantum/core/serialization.py
conductorquantum/environment.py
conductorquantum/errors/__init__.py
conductorquantum/errors/forbidden_error.py
conductorquantum/errors/not_found_error.py
conductorquantum/errors/unprocessable_entity_error.py
conductorquantum/model_results/__init__.py
conductorquantum/model_results/client.py
conductorquantum/model_results/raw_client.py
conductorquantum/models/__init__.py
conductorquantum/models/client.py
conductorquantum/models/extended_client.py
conductorquantum/models/raw_client.py
conductorquantum/py.typed
conductorquantum/types/__init__.py
conductorquantum/types/http_validation_error.py
conductorquantum/types/model_public.py
conductorquantum/types/model_result_public.py
conductorquantum/types/model_result_public_masked.py
conductorquantum/types/validation_error.py
conductorquantum/types/validation_error_loc_item.py
conductorquantum/version.py
conductorquantum-0.1.2.dist-info/METADATA
conductorquantum-0.1.2.dist-info/WHEEL
conductorquantum-0.1.2.dist-info/RECORD
